finvizfinance/__init__.py
finvizfinance/calendar.py
finvizfinance/constants.py
finvizfinance/crypto.py
finvizfinance/earnings.py
finvizfinance/forex.py
finvizfinance/future.py
finvizfinance/insider.py
finvizfinance/news.py
finvizfinance/quote.py
finvizfinance/util.py
finvizfinance/group/__init__.py
finvizfinance/group/base.py
finvizfinance/group/custom.py
finvizfinance/group/overview.py
finvizfinance/group/performance.py
finvizfinance/group/spectrum.py
finvizfinance/group/util.py
finvizfinance/group/valuation.py
finvizfinance/screener/__init__.py
finvizfinance/screener/base.py
finvizfinance/screener/custom.py
finvizfinance/screener/financial.py
finvizfinance/screener/overview.py
finvizfinance/screener/ownership.py
finvizfinance/screener/performance.py
finvizfinance/screener/technical.py
finvizfinance/screener/ticker.py
finvizfinance/screener/util.py
finvizfinance/screener/valuation.py
test/__init__.py
test/test_calendar.py
test/test_crypto.py
test/test_forex.py
test/test_group.py
test/test_insider.py
test/test_news.py
test/test_quote.py
test/test_screener.py
test/test_util.py
finvizfinance-1.0.0.dist-info/LICENSE
finvizfinance-1.0.0.dist-info/METADATA
finvizfinance-1.0.0.dist-info/WHEEL
finvizfinance-1.0.0.dist-info/top_level.txt
finvizfinance-1.0.0.dist-info/RECORD
