Metadata-Version: 2.1
Name: finvizfinance
Version: 1.0.0
Summary: Finviz Finance. Information downloader.
Home-page: https://github.com/lit26/finvizfinance
Author: Tianning Li
Author-email: ltianningli@gmail.com
License: The MIT License (MIT)
Classifier: Programming Language :: Python :: 3.9
Classifier: Programming Language :: Python :: 3.10
Classifier: Programming Language :: Python :: 3.11
Classifier: License :: OSI Approved :: MIT License
Requires-Python: >=3.9
License-File: LICENSE
Requires-Dist: pandas
Requires-Dist: requests
Requires-Dist: beautifulsoup4
Requires-Dist: lxml
